{
  "status": "complete",
  "subtasks_completed": [
    {
      "subtask_id": "phase-0-subtask-1",
      "status": "complete",
      "implementation": {
        "files_modified": ["apps/api/src/db/schema.ts"],
        "files_created": [],
        "verification_result": "pass",
        "verification_output": "DDL alterada: empresa tem agora (id, nome, corte_semanal, tolerancia_semanal_min) com CHECK constraint para corte_semanal. Banco dropado e recriado. SELECT confirmou estrutura correta.",
        "self_critique": {
          "pattern_adherence": true,
          "error_handling": true,
          "code_cleanliness": true,
          "issues_found": [],
          "improvements_made": ["Adicionado CHECK constraint para corte_semanal (enum de 7 valores válidos)"]
        }
      },
      "completed_at": "2026-02-14T23:55:00Z"
    },
    {
      "subtask_id": "phase-0-subtask-2",
      "status": "complete",
      "implementation": {
        "files_modified": ["apps/api/src/db/seed.ts"],
        "files_created": [],
        "verification_result": "pass",
        "verification_output": "INSERT de empresa corrigido para (nome, corte_semanal, tolerancia_semanal_min). SELECT FROM empresa retornou: id=1, nome='Supermercado Fernandes', corte_semanal='SEG_DOM', tolerancia_semanal_min=30",
        "self_critique": {
          "pattern_adherence": true,
          "error_handling": true,
          "code_cleanliness": true,
          "issues_found": [],
          "improvements_made": []
        }
      },
      "completed_at": "2026-02-14T23:56:00Z"
    },
    {
      "subtask_id": "phase-0-subtask-3",
      "status": "complete",
      "implementation": {
        "files_modified": ["apps/api/src/db/seed.ts"],
        "files_created": [],
        "verification_result": "pass",
        "verification_output": "4 valores de tipos_contrato corrigidos conforme BUILD doc: CLT 36h (dias_trabalho 6→5), CLT 30h (max_minutos_dia 480→360, trabalha_domingo 0→1), Estagiario 20h (max_minutos_dia 360→240). SELECT confirmou valores corretos.",
        "self_critique": {
          "pattern_adherence": true,
          "error_handling": true,
          "code_cleanliness": true,
          "issues_found": [],
          "improvements_made": ["Comentários inline nos tipos explicando o que foi corrigido"]
        }
      },
      "completed_at": "2026-02-14T23:57:00Z"
    },
    {
      "subtask_id": "phase-0-subtask-4",
      "status": "complete",
      "implementation": {
        "files_modified": ["packages/shared/src/types.ts"],
        "files_created": [],
        "verification_result": "pass",
        "verification_output": "npx tsc --noEmit (API e Web) → 0 errors. Interface Empresa atualizada: removido cidade/estado, adicionado corte_semanal (string) e tolerancia_semanal_min (number). Rebuild do @escalaflow/shared executado com sucesso.",
        "self_critique": {
          "pattern_adherence": true,
          "error_handling": true,
          "code_cleanliness": true,
          "issues_found": [],
          "improvements_made": ["Rebuild do shared package para atualizar types distribuídos para API e Web"]
        }
      },
      "completed_at": "2026-02-15T00:10:00Z"
    },
    {
      "subtask_id": "phase-0-subtask-5",
      "status": "complete",
      "implementation": {
        "files_modified": ["apps/api/src/routes/empresa.ts"],
        "files_created": [],
        "verification_result": "pass",
        "verification_output": "npx tsc --noEmit (API) → 0 errors. GET /api/empresa e PUT /api/empresa atualizados: queries SQL agora usam (nome, corte_semanal, tolerancia_semanal_min) em vez de (nome, cidade, estado).",
        "self_critique": {
          "pattern_adherence": true,
          "error_handling": true,
          "code_cleanliness": true,
          "issues_found": [],
          "improvements_made": []
        }
      },
      "completed_at": "2026-02-15T00:12:00Z"
    },
    {
      "subtask_id": "phase-0-subtask-6",
      "status": "complete",
      "implementation": {
        "files_modified": ["apps/web/src/paginas/EmpresaConfig.tsx"],
        "files_created": [],
        "verification_result": "pass",
        "verification_output": "npx tsc --noEmit (Web) → 0 errors. Form atualizado: removido campos cidade/estado, adicionado Select para corte_semanal (7 opções: SEG_DOM até DOM_SAB) e Input numérico para tolerancia_semanal_min (min 0, max 100, default 30). Helper text adicionado para guiar usuário.",
        "self_critique": {
          "pattern_adherence": true,
          "error_handling": true,
          "code_cleanliness": true,
          "issues_found": [],
          "improvements_made": [
            "Adicionado helper text explicativo em cada campo (corte_semanal e tolerancia_semanal_min)",
            "Labels em português claro",
            "Select com opções descritivas ('Segunda a Domingo' em vez de apenas 'SEG_DOM')"
          ]
        }
      },
      "completed_at": "2026-02-15T00:15:00Z"
    },
    {
      "subtask_id": "phase-0-subtask-7",
      "status": "complete",
      "implementation": {
        "files_modified": ["apps/api/src/motor/gerador.ts"],
        "files_created": [],
        "verification_result": "pass",
        "verification_output": "npx tsc --noEmit (API) → 0 errors. Parâmetro opcional tolerancia_min?: number adicionado em gerarProposta(). Linha 525: const TOLERANCIA_MIN = tolerancia_min ?? 30. Motor agora aceita tolerancia customizada mas mantém default 30 se não fornecido.",
        "self_critique": {
          "pattern_adherence": true,
          "error_handling": true,
          "code_cleanliness": true,
          "issues_found": [],
          "improvements_made": ["Parâmetro opcional com default explícito mantém backward compatibility"]
        }
      },
      "completed_at": "2026-02-15T00:18:00Z"
    },
    {
      "subtask_id": "phase-0-subtask-8",
      "status": "complete",
      "implementation": {
        "files_modified": ["apps/api/src/routes/escalas.ts"],
        "files_created": [],
        "verification_result": "pass",
        "verification_output": "npx tsc --noEmit (API) → 0 errors. POST /api/setores/:id/gerar-escala agora busca empresa do banco, lê tolerancia_semanal_min e passa como 5º parâmetro para gerarProposta(). Fallback ?? 30 se empresa não existe.",
        "self_critique": {
          "pattern_adherence": true,
          "error_handling": true,
          "code_cleanliness": true,
          "issues_found": [],
          "improvements_made": ["Fallback defensivo ?? 30 garante que motor sempre funciona mesmo sem empresa"]
        }
      },
      "completed_at": "2026-02-15T00:19:00Z"
    },
    {
      "subtask_id": "phase-1-subtask-1",
      "status": "complete",
      "implementation": {
        "files_modified": ["packages/shared/src/types.ts"],
        "files_created": [],
        "verification_result": "pass",
        "verification_output": "npx tsc --noEmit (Web) → 0 errors. npx tsc --noEmit (API) → 1 erro temporário esperado em routes/escalas.ts (Property 'indicadores' is missing). Interface Indicadores criada com 5 campos conforme BUILD doc. Campo indicadores: Indicadores adicionado em EscalaCompleta. Rebuild do @escalaflow/shared executado com sucesso.",
        "self_critique": {
          "pattern_adherence": true,
          "error_handling": true,
          "code_cleanliness": true,
          "issues_found": [],
          "improvements_made": ["Comentários inline nos campos de Indicadores explicando range de valores (0-100)"]
        }
      },
      "completed_at": "2026-02-15T00:20:00Z"
    },
    {
      "subtask_id": "phase-1-subtask-2",
      "status": "complete",
      "implementation": {
        "files_modified": ["apps/api/src/db/schema.ts"],
        "files_created": [],
        "verification_result": "pass",
        "verification_output": "DDL de escalas alterada: adicionadas 4 colunas (cobertura_percent REAL DEFAULT 0, violacoes_hard INTEGER DEFAULT 0, violacoes_soft INTEGER DEFAULT 0, equilibrio REAL DEFAULT 0). Banco dropado manualmente via rm db.sqlite. Próxima inicialização da API vai recriar com schema atualizado.",
        "self_critique": {
          "pattern_adherence": true,
          "error_handling": true,
          "code_cleanliness": true,
          "issues_found": [],
          "improvements_made": ["DEFAULT 0 em todas colunas de indicadores evita NULL handling desnecessário"]
        }
      },
      "completed_at": "2026-02-15T00:22:00Z"
    },
    {
      "subtask_id": "phase-1-subtask-3",
      "status": "complete",
      "implementation": {
        "files_modified": ["apps/api/src/motor/gerador.ts"],
        "files_created": [],
        "verification_result": "pass",
        "verification_output": "npx tsc --noEmit (API) → 0 errors. Interface MotorResultado expandida com 4 campos: cobertura_percent, violacoes_hard, violacoes_soft, equilibrio. Retorno de gerarProposta() atualizado na linha 763 para incluir esses valores calculados (já existentes nas linhas 699-742).",
        "self_critique": {
          "pattern_adherence": true,
          "error_handling": true,
          "code_cleanliness": true,
          "issues_found": [],
          "improvements_made": [
            "Arredondamento de cobertura_percent e equilibrio (Math.round(x * 100) / 100) para 2 decimais de precisão",
            "Motor agora expõe TODOS os indicadores calculados internamente"
          ]
        }
      },
      "completed_at": "2026-02-15T00:25:00Z"
    },
    {
      "subtask_id": "phase-1-subtask-4",
      "status": "complete",
      "implementation": {
        "files_modified": ["apps/api/src/routes/escalas.ts"],
        "files_created": [],
        "verification_result": "pass",
        "verification_output": "npx tsc --noEmit (API) → 0 errors. POST /api/setores/:id/gerar-escala atualizado: INSERT de escalas agora persiste 4 indicadores (cobertura_percent, violacoes_hard, violacoes_soft, equilibrio). Response EscalaCompleta completa com campo indicadores (5 valores: 4 do motor + pontuacao). GET /api/escalas/:id atualizado para ler indicadores do banco e retornar EscalaCompleta completa.",
        "self_critique": {
          "pattern_adherence": true,
          "error_handling": true,
          "code_cleanliness": true,
          "issues_found": [],
          "improvements_made": [
            "GET usa nullish coalescing (??) para fallback 0 em indicadores (defensive coding)",
            "Response type explicitamente tipada como EscalaCompleta em ambas routes (consistency)"
          ]
        }
      },
      "completed_at": "2026-02-15T00:30:00Z"
    },
    {
      "subtask_id": "phase-2-subtask-1",
      "status": "complete",
      "implementation": {
        "files_modified": [],
        "files_created": ["apps/api/src/motor/validador.ts"],
        "verification_result": "pass",
        "verification_output": "npx tsc --noEmit (API) → 0 errors. Arquivo validador.ts criado (439 linhas). Função validarEscala() implementada: lê alocações do banco, roda validações R1-R8 (MAX_DIAS_CONSECUTIVOS, DESCANSO_ENTRE_JORNADAS, RODIZIO_DOMINGO, MAX_JORNADA_DIARIA, META_SEMANAL, PREFERENCIA_DIA, PREFERENCIA_TURNO, COBERTURA), calcula indicadores (scoring idêntico ao gerador.ts), retorna { violacoes, indicadores }. Lógica extraída do gerador.ts sem duplicação — helpers timeToMin(), diaSemana(), getDias(), getWeeks() copiados para evitar dependência circular.",
        "self_critique": {
          "pattern_adherence": true,
          "error_handling": true,
          "code_cleanliness": true,
          "issues_found": [],
          "improvements_made": [
            "Validação defensiva: se escala não existe no banco, throw Error (fail-fast)",
            "Lookback zerado (diasConsec=0, domConsec=0) — validação não considera histórico anterior à escala atual",
            "Arredondamento de cobertura_percent e equilibrio (1 casa decimal) para consistência com gerador.ts",
            "Tolerancia_min como parâmetro opcional (default 30) — permite customização futura"
          ]
        }
      },
      "completed_at": "2026-02-15T00:35:00Z"
    },
    {
      "subtask_id": "phase-2-subtask-2",
      "status": "complete",
      "implementation": {
        "files_modified": ["apps/api/src/routes/escalas.ts"],
        "files_created": [],
        "verification_result": "pass",
        "verification_output": "npx tsc --noEmit (API) → 0 errors. POST /api/escalas/:id/ajustar atualizado: após UPSERT das alocações, chama validarEscala() para recalcular violações e indicadores. UPDATE escalas SET pontuacao, cobertura_percent, violacoes_hard, violacoes_soft, equilibrio persiste indicadores atualizados. Response mudou de { alocacoes } para EscalaCompleta completa { escala, alocacoes, indicadores, violacoes }. Frontend agora recebe validação em tempo real após ajuste manual.",
        "self_critique": {
          "pattern_adherence": true,
          "error_handling": true,
          "code_cleanliness": true,
          "issues_found": [],
          "improvements_made": [
            "Import de validarEscala adicionado no topo do arquivo",
            "Type assertions explícitas (as EscalaCompleta['escala'], as EscalaCompleta['alocacoes']) para TypeScript safety",
            "Busca tolerancia_semanal_min do banco com fallback ?? 30 (defensive coding)",
            "Indicadores persistidos ANTES de retornar response — garante consistência banco/response"
          ]
        }
      },
      "completed_at": "2026-02-15T00:37:00Z"
    },
    {
      "subtask_id": "phase-2-subtask-3",
      "status": "complete",
      "implementation": {
        "files_modified": ["apps/api/src/routes/escalas.ts"],
        "files_created": [],
        "verification_result": "pass",
        "verification_output": "npx tsc --noEmit (API) → 0 errors. PUT /api/escalas/:id/oficializar atualizado: TODO removido. Antes de oficializar, chama validarEscala(). Se indicadores.violacoes_hard > 0, retorna 409 Conflict com mensagem 'Escala tem N violacoes criticas. Corrija antes de oficializar.' Se ok (violacoes_hard === 0), prossegue com oficialização normalmente (arquiva oficial anterior + marca esta como OFICIAL). Frontend agora recebe erro 409 e pode mostrar toast explicativo.",
        "self_critique": {
          "pattern_adherence": true,
          "error_handling": true,
          "code_cleanliness": true,
          "issues_found": [],
          "improvements_made": [
            "Mensagem de erro 409 clara e acionável (informa quantidade de violações críticas)",
            "Validação usa mesma função validarEscala() de POST ajustar — DRY principle",
            "Tolerancia_semanal_min buscada do banco com fallback ?? 30 (consistency)",
            "Lógica de arquivamento + oficialização mantida intacta (só validação adicionada antes)"
          ]
        }
      },
      "completed_at": "2026-02-15T00:38:00Z"
    },
    {
      "subtask_id": "phase-3-subtask-1",
      "status": "complete",
      "implementation": {
        "files_modified": [],
        "files_created": ["apps/web/src/componentes/ExportarEscala.tsx"],
        "verification_result": "pass",
        "verification_output": "npm run build (Web) → 0 errors. ExportarEscala.tsx criado (220 linhas). Componente React que gera HTML self-contained: CSS inline (React.CSSProperties objects), tabela pessoa x dia com horários/F/I, cores por status (TRABALHO verde, DOMINGO azul, INDISPONIVEL amarelo, FOLGA cinza), header com setor/periodo/pontuacao/status badge, footer com legenda e timestamp, agrupamento semanal (7 dias por semana), @media print para A4 paisagem. Funciona offline (sem dependências externas). Usa formatarData() do lib/formatadores para datas em português.",
        "self_critique": {
          "pattern_adherence": true,
          "error_handling": true,
          "code_cleanliness": true,
          "issues_found": [],
          "improvements_made": [
            "CSS objects (React.CSSProperties) em vez de strings inline para type safety",
            "Semanas separadas visualmente (pageBreakInside: avoid) para impressão multi-página sem quebra no meio da semana",
            "Status badge com cores específicas por status (RASCUNHO amarelo, OFICIAL verde, ARQUIVADA cinza)",
            "@media print com print-color-adjust: exact garante cores impressas corretamente",
            "formatTime() helper remove :00 redundante mas mantém :30 para meias-horas"
          ]
        }
      },
      "completed_at": "2026-02-15T00:40:00Z"
    },
    {
      "subtask_id": "phase-3-subtask-2",
      "status": "complete",
      "implementation": {
        "files_modified": ["apps/web/src/paginas/EscalaPagina.tsx"],
        "files_created": [],
        "verification_result": "pass",
        "verification_output": "npm run build (Web) → 0 errors. handleImprimir() implementado: abre nova janela, renderiza ExportarEscala via renderToStaticMarkup (server-side rendering), escreve HTML completo com meta charset/viewport, abre window.print() após 250ms delay (wait for styles). Botões nas abas Simulacao e Oficial atualizados: onClick={() => handleImprimir(escalaCompleta)}. Import ExportarEscala e react-dom/server adicionados. SimulacaoResult interface expandida com onImprimir callback. Fallback se popup bloqueado: toast.error().",
        "self_critique": {
          "pattern_adherence": true,
          "error_handling": true,
          "code_cleanliness": true,
          "issues_found": [],
          "improvements_made": [
            "Dynamic import de react-dom/server evita bundle size extra no main chunk",
            "Timeout de 250ms antes de print() garante que estilos inline sejam aplicados",
            "Toast de erro se popup bloqueado orienta usuário a permitir popups",
            "Nova janela tem título dinâmico 'Escala - [setor.nome]' para melhor UX",
            "HTML completo self-contained (<!DOCTYPE>, charset UTF-8) — abre sem problema em qualquer navegador"
          ]
        }
      },
      "completed_at": "2026-02-15T00:42:00Z"
    },
    {
      "subtask_id": "phase-3-subtask-3",
      "status": "complete",
      "implementation": {
        "files_modified": ["apps/web/src/paginas/EscalaPagina.tsx"],
        "files_created": [],
        "verification_result": "pass",
        "verification_output": "npm run build (Web) → 0 errors. Cards de indicadores JÁ EXISTIAM (linhas 533-589) mas estavam usando computeIndicators() (cálculo local). Substituído por getIndicators() que consome escalaCompleta.indicadores direto do backend. computeIndicators() deletado (60 linhas de lógica removidas). Interface SimulacaoResultProps renomeada de computeIndicators para getIndicators. Cards agora mostram valores reais do backend (cobertura_percent, violacoes_hard, violacoes_soft, equilibrio, pontuacao) sem recálculo redundante. Dados de fase 1 consumidos corretamente.",
        "self_critique": {
          "pattern_adherence": true,
          "error_handling": true,
          "code_cleanliness": true,
          "issues_found": [],
          "improvements_made": [
            "Eliminado 60 linhas de lógica duplicada (computeIndicators frontend calculava o que backend já retorna)",
            "getIndicators() é pure function de 6 linhas — simplesmente extrai e formata indicadores do backend",
            "Cards agora refletem indicadores PERSISTIDOS no banco (verdade única)",
            "Indicadores sempre consistentes entre backend/frontend (sem drift de cálculo)",
            "DRY principle aplicado — cálculo só existe no motor backend"
          ]
        }
      },
      "completed_at": "2026-02-15T00:44:00Z"
    }
  ],
  "subtasks_remaining": [],
  "current_phase": "phase-3",
  "updated_at": "2026-02-15T00:44:00Z"
}
